mergeBams/__init__.py
mergeBams/__main__.py
mergeBams/mergeBams.py
mergeBams/piperna.py
mergeBams-0.14.dist-info/METADATA
mergeBams-0.14.dist-info/WHEEL
mergeBams-0.14.dist-info/entry_points.txt
mergeBams-0.14.dist-info/top_level.txt
mergeBams-0.14.dist-info/RECORD
