Metadata-Version: 2.1
Name: mergeBams
Version: 0.14
Summary: Merge sam/bam files with intelligent cell barcode preservation
Home-page: https://github.com/scfurl/mergeBams.git
Author: Scott Furlan
Author-email: scottfurlan@gmail.com
License: UNKNOWN
Platform: UNKNOWN
Classifier: Programming Language :: Python :: 3
Classifier: License :: OSI Approved :: MIT License
Classifier: Operating System :: OS Independent
Requires-Python: >=2.5
